id57-1.0.0.dist-info/METADATA
id57-1.0.0.dist-info/WHEEL
id57-1.0.0.dist-info/licenses/LICENSE
id57/__init__.py
id57/_core.abi3.so
id57/_core.pyi
id57/_fallback.py
id57-1.0.0.dist-info/RECORD
