Metadata-Version: 2.4
Name: id57
Version: 1.0.0
Classifier: Development Status :: 5 - Production/Stable
Classifier: Intended Audience :: Developers
Classifier: License :: OSI Approved :: MIT License
Classifier: Operating System :: OS Independent
Classifier: Programming Language :: Python
Classifier: Programming Language :: Python :: 3
Classifier: Programming Language :: Python :: 3.9
Classifier: Programming Language :: Python :: 3.10
Classifier: Programming Language :: Python :: 3.11
Classifier: Programming Language :: Python :: 3.12
Classifier: Programming Language :: Python :: 3.13
Classifier: Programming Language :: Rust
Classifier: Topic :: Software Development :: Libraries
Classifier: Topic :: Software Development :: Libraries :: Python Modules
Requires-Dist: pytest>=8.3 ; extra == 'dev'
Requires-Dist: pytest-cov>=5.0 ; extra == 'dev'
Requires-Dist: maturin>=1.5 ; extra == 'dev'
Provides-Extra: dev
License-File: LICENSE
Summary: Rust-backed helpers for Artemis-style base-57 identifiers
Keywords: identifier,uuid,base57,artemis
Author: Alex Ogeny
Requires-Python: >=3.9
Project-URL: Homepage, https://github.com/alexogeny/id57
Project-URL: Repository, https://github.com/alexogeny/id57
Project-URL: Issues, https://github.com/alexogeny/id57/issues
